[
    {
        "key": "group_enterfullscreen",
        "title": "Modul startowy - pelen ekran",
        "fields": [
            {
                "key": "field_5cc1bd9a6ef27",
                "label": "Modul startowy - pelen ekran",
                "name": "",
                "type": "accordion",
                "instructions": "",
                "required": 0,
                "conditional_logic": 0,
                "wrapper": {
                    "width": "",
                    "class": "",
                    "id": ""
                },
                "open": 0,
                "multi_expand": 0,
                "endpoint": 0
            }
        ],
        "location": [
            [
                {
                    "param": "block",
                    "operator": "==",
                    "value": "acf\/enterfullscreen"
                }
            ]
        ],
        "menu_order": 0,
        "position": "normal",
        "style": "default",
        "label_placement": "top",
        "instruction_placement": "label",
        "hide_on_screen": "",
        "active": 1,
        "description": ""
    }
]